infinity_client/__init__.py
infinity_client/api/__init__.py
infinity_client/api/default/__init__.py
infinity_client/api/default/classify.py
infinity_client/api/default/embeddings.py
infinity_client/api/default/embeddings_audio.py
infinity_client/api/default/embeddings_image.py
infinity_client/api/default/health.py
infinity_client/api/default/metrics_metrics_get.py
infinity_client/api/default/models.py
infinity_client/api/default/redirect_get.py
infinity_client/api/default/rerank.py
infinity_client/client.py
infinity_client/errors.py
infinity_client/models/__init__.py
infinity_client/models/audio_embedding_input.py
infinity_client/models/classify_input.py
infinity_client/models/classify_object.py
infinity_client/models/classify_result.py
infinity_client/models/classify_result_object.py
infinity_client/models/embedding_encoding_format.py
infinity_client/models/embedding_object.py
infinity_client/models/embedding_object_object.py
infinity_client/models/http_validation_error.py
infinity_client/models/image_embedding_input.py
infinity_client/models/model_info.py
infinity_client/models/model_info_object.py
infinity_client/models/model_info_owned_by.py
infinity_client/models/open_ai_embedding_input_audio.py
infinity_client/models/open_ai_embedding_input_audio_modality.py
infinity_client/models/open_ai_embedding_input_image.py
infinity_client/models/open_ai_embedding_input_image_modality.py
infinity_client/models/open_ai_embedding_input_text.py
infinity_client/models/open_ai_embedding_input_text_modality.py
infinity_client/models/open_ai_embedding_result.py
infinity_client/models/open_ai_embedding_result_object.py
infinity_client/models/open_ai_model_info.py
infinity_client/models/re_rank_object.py
infinity_client/models/re_rank_result.py
infinity_client/models/re_rank_result_object.py
infinity_client/models/rerank_input.py
infinity_client/models/response_health.py
infinity_client/models/stats.py
infinity_client/models/usage.py
infinity_client/models/validation_error.py
infinity_client-0.0.77.dist-info/METADATA
infinity_client-0.0.77.dist-info/WHEEL
infinity_client-0.0.77.dist-info/RECORD
